setup.py
xcanvas/__init__.py
xcanvas/test.py
xcanvas/xcanvas.py
xcanvas.egg-info/PKG-INFO
xcanvas.egg-info/SOURCES.txt
xcanvas.egg-info/dependency_links.txt
xcanvas.egg-info/not-zip-safe
xcanvas.egg-info/top_level.txt