Metadata-Version: 1.0
Name: xcanvas
Version: 1.21
Summary: Extended tkinter canvas class
Home-page: http://github.com/samyzaf/xcanvas
Author: Samy Zafrany
Author-email: admin@samyzaf.com
License: MIT
Platform: UNKNOWN
